README.md
setup.cfg
setup.py
restdbio_api_wrapper/__init__.py
restdbio_api_wrapper.egg-info/PKG-INFO
restdbio_api_wrapper.egg-info/SOURCES.txt
restdbio_api_wrapper.egg-info/dependency_links.txt
restdbio_api_wrapper.egg-info/requires.txt
restdbio_api_wrapper.egg-info/top_level.txt
restdbio_api_wrapper/Connection/Connection.py
restdbio_api_wrapper/Connection/__init__.py
restdbio_api_wrapper/apis/CollectionAPI.py
restdbio_api_wrapper/apis/__init__.py
restdbio_api_wrapper/utils/Decorators.py
restdbio_api_wrapper/utils/Exceptions.py
restdbio_api_wrapper/utils/__init__.py