Metadata-Version: 2.1
Name: restdbio-api-wrapper
Version: 0.0.12
Summary: An API Wrapper written for restdb.io which helps host online databases.
Home-page: https://github.com/hseysen/restdbio_api_wrapper
Author: Hasan Isgandarli
Author-email: hesenisgenderli999@gmail.com
License: GNU General Public License v3 (GPLv3)
Download-URL: https://github.com/hseysen/restdbio_api_wrapper/archive/v0.0.12-alpha.tar.gz
Keywords: api wrapper restdbio online database
Platform: UNKNOWN
Classifier: Development Status :: 3 - Alpha
Classifier: Intended Audience :: Developers
Classifier: Programming Language :: Python :: 3
Classifier: Topic :: Database
Classifier: License :: OSI Approved :: GNU General Public License v3 (GPLv3)
